setup.py
pymcdream/__init__.py
pymcdream/dream.py
pymcdream/rand_no_replace.c
pymcdream.egg-info/PKG-INFO
pymcdream.egg-info/SOURCES.txt
pymcdream.egg-info/dependency_links.txt
pymcdream.egg-info/requires.txt
pymcdream.egg-info/top_level.txt