Metadata-Version: 1.0
Name: pymcdream
Version: 0.1.1
Summary: Implements DREAM in Python based on PyMC for exploratory purposes
Home-page: pypi.python.org/pypi/dream
Author: John Salvatier
Author-email: jsalvati@u.washington.edu
License: BSD
Platform: UNKNOWN
Classifier: Development Status :: 2 - Pre-Alpha
Classifier: Programming Language :: Python
Classifier: License :: OSI Approved :: BSD License
Classifier: Intended Audience :: Science/Research
Classifier: Topic :: Scientific/Engineering
Classifier: Topic :: Scientific/Engineering :: Mathematics
Classifier: Operating System :: OS Independent
